hat/translator/__main__.py
hat/translator/common.py
hat/translator/main.py
hat_translator-0.4.0.dev202012042345.dist-info/METADATA
hat_translator-0.4.0.dev202012042345.dist-info/WHEEL
hat_translator-0.4.0.dev202012042345.dist-info/entry_points.txt
hat_translator-0.4.0.dev202012042345.dist-info/top_level.txt
hat_translator-0.4.0.dev202012042345.dist-info/RECORD
