Metadata-Version: 2.1
Name: hat-translator
Version: 0.4.0.dev202012042345
Summary: Hat configuration transformation interface
Home-page: https://github.com/hat-open/hat-core
License: MIT
Platform: UNKNOWN
Classifier: Programming Language :: Python :: 3
Classifier: License :: OSI Approved :: MIT License
Requires-Python: >=3.8
Requires-Dist: hat-util
Requires-Dist: hat-json
